[{"line":1,"elements":[{"start_timestamp":"2023-12-09T14:30:21.880Z","before":[{"result":{"duration":1624656200,"status":"passed"},"match":{"location":"hooks.HooksAPI.setUpApi()"}}],"line":4,"name":"When a valid GET request is sent to the 'user/list/loan' endpoint with the appropriate","description":"  authorization credentials, it should return a status code of 200, and the response remark should be \"success\"","id":"as-a-user--ı-want-to-access-the-list-of-loans-via-apı-connection.;when-a-valid-get-request-is-sent-to-the--user/list/loan--endpoint-with-the-appropriate","type":"scenario","keyword":"Scenario","steps":[{"result":{"duration":74798300,"status":"passed"},"line":7,"name":"The API user sets \"user/list/loan\" path parameters","match":{"arguments":[{"val":"\"user/list/loan\"","offset":18}],"location":"stepdefinitions.API_UserStepdefinitions.the_apı_user_sets_path_parameters(java.lang.String)"},"keyword":"Given "},{"result":{"duration":4305124100,"status":"passed"},"line":8,"name":"The API user saves the response returned from the user list loan endpoint","match":{"location":"stepdefinitions.API_UserStepdefinitions.theAPIUserSavesTheResponseReturnedFromTheUserListLoanEndpoint()"},"keyword":"And "},{"result":{"duration":69812800,"status":"passed"},"line":9,"name":"The API user verifies that the status code is 200","match":{"arguments":[{"val":"200","offset":46}],"location":"stepdefinitions.API_UserStepdefinitions.theAPIUserVerifiesThatTheStatusCodeIs(int)"},"keyword":"Then "},{"result":{"duration":115691700,"status":"passed"},"line":10,"name":"The API user verifies that the remark information in the response body is \"success\"","match":{"arguments":[{"val":"\"success\"","offset":74}],"location":"stepdefinitions.API_UserStepdefinitions.theAPIUserVerifiesThatTheRemarkInformationInTheResponseBodyIs(java.lang.String)"},"keyword":"And "}],"tags":[{"name":"@API"}]}],"name":"As a user, I want to access the list of loans via API connection.","description":"","id":"as-a-user--ı-want-to-access-the-list-of-loans-via-apı-connection.","keyword":"Feature","uri":"file:src/test/resources/API/User/Other/ListLoan.feature","tags":[]}]